eg4_solar_client/__init__.py
eg4_solar_client/client.py
eg4_solar_client-0.1.1.dist-info/METADATA
eg4_solar_client-0.1.1.dist-info/WHEEL
eg4_solar_client-0.1.1.dist-info/licenses/LICENSE
eg4_solar_client-0.1.1.dist-info/RECORD
